ctx_defense/__init__.py
ctx_defense/app.py
ctx_defense/permuters.py
ctx_defense-1.0.0.dist-info/DESCRIPTION.rst
ctx_defense-1.0.0.dist-info/LICENSE.txt
ctx_defense-1.0.0.dist-info/METADATA
ctx_defense-1.0.0.dist-info/RECORD
ctx_defense-1.0.0.dist-info/WHEEL
ctx_defense-1.0.0.dist-info/metadata.json
ctx_defense-1.0.0.dist-info/top_level.txt
