Metadata-Version: 2.0
Name: ctx-defense
Version: 1.0.0
Summary: The CTX defense library.
Home-page: https://github.com/dimkarakostas/ctx
Author: Dimitris Karakostas
Author-email: dimit.karakostas@gmail.com
License: MIT
Download-URL: https://github.com/dimkarakostas/ctx
Keywords: ctx defense compression security BREACH
Platform: UNKNOWN
Classifier: Development Status :: 3 - Alpha
Classifier: Environment :: Web Environment
Classifier: Intended Audience :: Developers
Classifier: License :: OSI Approved :: MIT License
Classifier: Operating System :: OS Independent
Classifier: Programming Language :: Python
Classifier: Programming Language :: Python :: 2
Classifier: Programming Language :: Python :: 2.7
Classifier: Topic :: Security
Classifier: Topic :: Security :: Cryptography
